proxup/__init__.py
proxup-0.1.1.dist-info/METADATA
proxup-0.1.1.dist-info/WHEEL
proxup-0.1.1.dist-info/top_level.txt
proxup-0.1.1.dist-info/RECORD
