Metadata-Version: 2.4
Name: proxup
Version: 0.1.1
Summary: Get proxies for free and automatically without any hassle.
Home-page: https://github.com/zZarby/ProxUp
Author: Zarby
Author-email: ZarbyTheOne@proton.me
Classifier: Programming Language :: Python :: 3
Classifier: License :: OSI Approved :: MIT License
Classifier: Operating System :: OS Independent
Requires-Python: >=3.6
Dynamic: author
Dynamic: author-email
Dynamic: classifier
Dynamic: description
Dynamic: description-content-type
Dynamic: home-page
Dynamic: requires-python
Dynamic: summary
